metaspector/__init__.py
metaspector/_exceptions.py
metaspector/cli.py
metaspector/inspector.py
metaspector/parsers.py
metaspector/format_handlers/__init__.py
metaspector/format_handlers/base.py
metaspector/format_handlers/flac/__init__.py
metaspector/format_handlers/flac/flac.py
metaspector/format_handlers/flac/flac_boxes.py
metaspector/format_handlers/flac/flac_utils.py
metaspector/format_handlers/mp3/__init__.py
metaspector/format_handlers/mp3/mp3.py
metaspector/format_handlers/mp3/mp3_boxes.py
metaspector/format_handlers/mp3/mp3_utils.py
metaspector/format_handlers/mp4/__init__.py
metaspector/format_handlers/mp4/mp4.py
metaspector/format_handlers/mp4/mp4_bitstream_parser.py
metaspector/format_handlers/mp4/mp4_boxes.py
metaspector/format_handlers/mp4/mp4_utils.py
metaspector/matrices/__init__.py
metaspector/matrices/language_matrix.py
metaspector/matrices/rating_matrix.py
metaspector-0.1.8.dist-info/licenses/LICENSE
metaspector-0.1.8.dist-info/METADATA
metaspector-0.1.8.dist-info/WHEEL
metaspector-0.1.8.dist-info/entry_points.txt
metaspector-0.1.8.dist-info/top_level.txt
metaspector-0.1.8.dist-info/RECORD
