Metadata-Version: 2.4
Name: metaspector
Version: 0.1.8
Summary: Python library to inspect and export metadata from MP4/M4V/M4A, MP3 and FLAC media files.
Author: RSMVDL
License-Expression: BSD-3-Clause
Project-URL: Homepage, https://github.com/rsmvdl/metaspector
Project-URL: Bug Tracker, https://github.com/rsmvdl/metaspector/issues
Classifier: Programming Language :: Python :: 3
Classifier: Operating System :: OS Independent
Classifier: Topic :: Multimedia :: Video
Requires-Python: >=3.6
License-File: LICENSE
Dynamic: license-file
